[
  {
    "id": 1,
    "pool": "5tKeEuW2syo3wXDBFRhZPkYg4YtCNyjwd6zj5oTXnPVh",
    "token_pair": "GLUE/SOL",
    "confidence": 0.887,
    "trigger": {
      "type": "wallet_entry",
      "wallet": "BocpMHmUePwamZcBxhRmb8YUVrqqhr6AkzdazosijSrM",
      "wallet_score": 93.2,
      "wallet_wr": 1
    },
    "pool_metrics": {
      "fee_apr": 0.0814,
      "volume_24h": 3282,
      "tvl": 37539,
      "fee_tvl_ratio": 0.0814,
      "organic_score": 75
    },
    "suggested": {
      "bin_step": 100,
      "range_lower": null,
      "range_upper": null
    },
    "validation_reasons": [
      "top_wallet_entered",
      "pool_passed_screening"
    ],
    "created_at": 1782438770
  },
  {
    "id": 1,
    "pool": "H4uj7z5LExamnP127jAQ5zsk2uqhLrqB3JttMMmZLdNx",
    "token_pair": "KLED/SOL",
    "confidence": 0.965,
    "trigger": {
      "type": "wallet_entry",
      "wallet": "XY2joC2DwF2HH1UAVUegiKYDPXLcgvXwTPZfxQRWn3k",
      "wallet_score": 91.2,
      "wallet_wr": 1
    },
    "pool_metrics": {
      "fee_apr": 0.0651,
      "volume_24h": 156216,
      "tvl": 203746,
      "fee_tvl_ratio": 0.0651,
      "organic_score": 75
    },
    "suggested": {
      "bin_step": 100,
      "range_lower": null,
      "range_upper": null
    },
    "validation_reasons": [
      "top_wallet_entered",
      "pool_passed_screening"
    ],
    "created_at": 1782499561
  },
  {
    "id": 2,
    "pool": "CFewdGnZGJjN1PYKxGFpAzFq1Eq1XMVZns1ksWsWHsXA",
    "token_pair": "TEST/SOL",
    "confidence": 0.82,
    "trigger": {
      "type": "wallet_entry",
      "wallet": "BocpMHmUePwamZcBxhRmb8YUVrqqhr6AkzdazosijSrM",
      "wallet_score": 75,
      "wallet_wr": 0.45
    },
    "pool_metrics": {
      "fee_apr": 5.5,
      "volume_24h": 150000,
      "tvl": 45000
    },
    "suggested": {
      "bin_step": 100,
      "range_lower": -5,
      "range_upper": 5
    },
    "validation_reasons": [
      "high fee apr",
      "top wallet entry"
    ],
    "created_at": 1782500392
  },
  {
    "id": 3,
    "pool": "HEB7r3kVJLhocbWsgYSgQrTo88GRAtH29gX1ev3Cd9hX",
    "token_pair": "ZERO/SOL",
    "confidence": 0.909,
    "trigger": {
      "type": "wallet_entry",
      "wallet": "XY2joC2DwF2HH1UAVUegiKYDPXLcgvXwTPZfxQRWn3k",
      "wallet_score": 91.2,
      "wallet_wr": 1
    },
    "pool_metrics": {
      "fee_apr": 0.051,
      "volume_24h": 5526,
      "tvl": 94794,
      "fee_tvl_ratio": 0.051,
      "organic_score": 80
    },
    "suggested": {
      "bin_step": 100,
      "range_lower": null,
      "range_upper": null
    },
    "validation_reasons": [
      "top_wallet_entered",
      "pool_passed_screening"
    ],
    "created_at": 1782502203
  },
  {
    "id": 4,
    "pool": "HEB7r3kVJLhocbWsgYSgQrTo88GRAtH29gX1ev3Cd9hX",
    "token_pair": "ZERO/SOL",
    "confidence": 0.908,
    "trigger": {
      "type": "wallet_entry",
      "wallet": "8ryctvNwpJTuuap3wuNTfcyEx4DjSuXvhGXSDHNaU8sQ",
      "wallet_score": 90.8,
      "wallet_wr": 0.9
    },
    "pool_metrics": {
      "fee_apr": 0.051,
      "volume_24h": 5526,
      "tvl": 94794,
      "fee_tvl_ratio": 0.051,
      "organic_score": 80
    },
    "suggested": {
      "bin_step": 100,
      "range_lower": null,
      "range_upper": null
    },
    "validation_reasons": [
      "top_wallet_entered",
      "pool_passed_screening"
    ],
    "created_at": 1782502205
  },
  {
    "id": 5,
    "pool": "EHY2sVmgfn18R27nsXYemnxDQMjtvCGCjwsYB9qoH6rU",
    "token_pair": "piss/SOL",
    "confidence": 0.924,
    "trigger": {
      "type": "wallet_entry",
      "wallet": "BocpMHmUePwamZcBxhRmb8YUVrqqhr6AkzdazosijSrM",
      "wallet_score": 90.6,
      "wallet_wr": 0.95
    },
    "pool_metrics": {
      "fee_apr": 0.1318,
      "volume_24h": 2858,
      "tvl": 10993,
      "fee_tvl_ratio": 0.1318,
      "organic_score": 75
    },
    "suggested": {
      "bin_step": 100,
      "range_lower": null,
      "range_upper": null
    },
    "validation_reasons": [
      "top_wallet_entered",
      "pool_passed_screening"
    ],
    "created_at": 1782502208
  },
  {
    "id": 6,
    "pool": "FuCNgSG8tKsY1LDUGJ7ZtNHdHV4dCtHNuFwvMYmiMUZm",
    "token_pair": "滑る猫/SOL",
    "confidence": 0.962,
    "trigger": {
      "type": "wallet_entry",
      "wallet": "BocpMHmUePwamZcBxhRmb8YUVrqqhr6AkzdazosijSrM",
      "wallet_score": 90.6,
      "wallet_wr": 0.95
    },
    "pool_metrics": {
      "fee_apr": 0.0969,
      "volume_24h": 3160,
      "tvl": 53629,
      "fee_tvl_ratio": 0.0969,
      "organic_score": 77
    },
    "suggested": {
      "bin_step": 100,
      "range_lower": null,
      "range_upper": null
    },
    "validation_reasons": [
      "top_wallet_entered",
      "pool_passed_screening"
    ],
    "created_at": 1782543608
  },
  {
    "id": 7,
    "pool": "FuCNgSG8tKsY1LDUGJ7ZtNHdHV4dCtHNuFwvMYmiMUZm",
    "token_pair": "滑る猫/SOL",
    "confidence": 0.883,
    "trigger": {
      "type": "wallet_entry",
      "wallet": "ByqbRLMcszhmxJhwcGcspLrQYKhCJqzr7DLBovrcoQSS",
      "wallet_score": 70.8,
      "wallet_wr": 0.9411764705882352
    },
    "pool_metrics": {
      "fee_apr": 0.0969,
      "volume_24h": 3160,
      "tvl": 53629,
      "fee_tvl_ratio": 0.0969,
      "organic_score": 77
    },
    "suggested": {
      "bin_step": 100,
      "range_lower": null,
      "range_upper": null
    },
    "validation_reasons": [
      "top_wallet_entered",
      "pool_passed_screening"
    ],
    "created_at": 1782545429
  },
  {
    "id": 8,
    "pool": "FuCNgSG8tKsY1LDUGJ7ZtNHdHV4dCtHNuFwvMYmiMUZm",
    "token_pair": "滑る猫/SOL",
    "confidence": 0.852,
    "trigger": {
      "type": "wallet_entry",
      "wallet": "ACLDRXeDHyEu92TCn5bRYNk834DHiP2GsF9ifwTYALCU",
      "wallet_score": 62.96,
      "wallet_wr": 1
    },
    "pool_metrics": {
      "fee_apr": 0.0969,
      "volume_24h": 3160,
      "tvl": 53629,
      "fee_tvl_ratio": 0.0969,
      "organic_score": 77
    },
    "suggested": {
      "bin_step": 100,
      "range_lower": null,
      "range_upper": null
    },
    "validation_reasons": [
      "top_wallet_entered",
      "pool_passed_screening"
    ],
    "created_at": 1782545437
  },
  {
    "id": 9,
    "pool": "Gaxi5m3avwdorhxasCQMnAZTXwuFaEXYXaDNWNXa4EoT",
    "token_pair": "Chameleon/SOL",
    "confidence": 0.962,
    "trigger": {
      "type": "wallet_entry",
      "wallet": "BocpMHmUePwamZcBxhRmb8YUVrqqhr6AkzdazosijSrM",
      "wallet_score": 90.6,
      "wallet_wr": 0.95
    },
    "pool_metrics": {
      "fee_apr": 0.0983,
      "volume_24h": 1498,
      "tvl": 30875,
      "fee_tvl_ratio": 0.0983,
      "organic_score": 82
    },
    "suggested": {
      "bin_step": 100,
      "range_lower": null,
      "range_upper": null
    },
    "validation_reasons": [
      "top_wallet_entered",
      "pool_passed_screening"
    ],
    "created_at": 1782547208
  },
  {
    "id": 10,
    "pool": "Gaxi5m3avwdorhxasCQMnAZTXwuFaEXYXaDNWNXa4EoT",
    "token_pair": "Chameleon/SOL",
    "confidence": 0.913,
    "trigger": {
      "type": "wallet_entry",
      "wallet": "t76wt98dvCzuQUPPgnAsc29ouZSzhBQqWdbVnzTa2Pe",
      "wallet_score": 78.2,
      "wallet_wr": 0.85
    },
    "pool_metrics": {
      "fee_apr": 0.0983,
      "volume_24h": 1498,
      "tvl": 30875,
      "fee_tvl_ratio": 0.0983,
      "organic_score": 82
    },
    "suggested": {
      "bin_step": 100,
      "range_lower": null,
      "range_upper": null
    },
    "validation_reasons": [
      "top_wallet_entered",
      "pool_passed_screening"
    ],
    "created_at": 1782549018
  }
]